{"cameraMode":{"drawMode":0,"name":"Shaded","section":"Shading Mode"},"sceneLighting":false,"audioPlay":false,"sceneViewState":{"m_AlwaysRefresh":false,"showFog":true,"showSkybox":false,"showFlares":true,"showImageEffects":true,"showParticleSystems":true,"showVisualEffectGraphs":true,"m_FxEnabled":true},"in2DMode":false,"pivot":{"x":313.3088684082031,"y":85.0050048828125,"z":0.605224609375},"rotation":{"x":0.006903619505465031,"y":0.28551724553108218,"z":0.002009573858231306,"w":-0.9583792090415955},"size":1050.572998046875,"orthographic":false}